sqlutilities/__init__.py
sqlutilities/_version.py
sqlutilities/connections/__init__.py
sqlutilities/connections/database_connection.py
sqlutilities/core/__init__.py
sqlutilities/core/enums.py
sqlutilities/core/types.py
sqlutilities/credentials/__init__.py
sqlutilities/credentials/aws_secrets.py
sqlutilities/credentials/azure_secrets.py
sqlutilities/credentials/gcp_secrets.py
sqlutilities/credentials/keyring_store.py
sqlutilities/credentials/vault_secrets.py
sqlutilities/download/__init__.py
sqlutilities/download/read_sql.py
sqlutilities/drivers/__init__.py
sqlutilities/drivers/builder.py
sqlutilities/drivers/factory.py
sqlutilities/drivers/models.py
sqlutilities/drivers/registry.py
sqlutilities/drivers/type_mapping.py
sqlutilities/errors/__init__.py
sqlutilities/errors/patterns.py
sqlutilities/errors/registry.py
sqlutilities/tables/__init__.py
sqlutilities/tables/definitions.py
sqlutilities/tables/table.py
sqlutilities/transactions/__init__.py
sqlutilities/transactions/config.py
sqlutilities/transactions/transaction.py
sqlutilities/validation/__init__.py
sqlutilities/validation/identifiers.py
sqlutilities-0.1.2.dist-info/licenses/LICENSE
sqlutilities-0.1.2.dist-info/METADATA
sqlutilities-0.1.2.dist-info/WHEEL
sqlutilities-0.1.2.dist-info/top_level.txt
sqlutilities-0.1.2.dist-info/RECORD
