Metadata-Version: 2.4
Name: SQLUtilities
Version: 0.1.2
Summary: A comprehensive Python library for unified database operations across multiple SQL database systems
Author-email: Matthew Ruppert <deceits.steamer-7e@icloud.com>
License: MIT
Project-URL: Homepage, https://github.com/ruppert20/SQLUtils-Python
Project-URL: Repository, https://github.com/ruppert20/SQLUtils-Python
Project-URL: Issues, https://github.com/ruppert20/SQLUtils-Python/issues
Keywords: sql,database,mysql,postgresql,oracle,sqlserver,bigquery,redshift,sqlite
Classifier: Development Status :: 4 - Beta
Classifier: Intended Audience :: Developers
Classifier: Programming Language :: Python :: 3
Classifier: Programming Language :: Python :: 3.12
Classifier: Programming Language :: Python :: 3.13
Classifier: Topic :: Database
Classifier: Topic :: Software Development :: Libraries :: Python Modules
Requires-Python: >=3.12
License-File: LICENSE
Requires-Dist: CoreUtilities>=0.0.1
Requires-Dist: sqlglot>=27.29.0
Requires-Dist: Unidecode>=1.4.0
Requires-Dist: pandas>=2.0.0
Requires-Dist: sqlalchemy>=2.0.44
Provides-Extra: mysql
Requires-Dist: PyMySQL>=1.1.2; extra == "mysql"
Requires-Dist: mysql-connector-python>=9.3.0; extra == "mysql"
Requires-Dist: mysqlclient>=2.2.0; extra == "mysql"
Provides-Extra: postgres
Requires-Dist: psycopg2-binary>=2.9.11; extra == "postgres"
Requires-Dist: psycopg>=3.1.0; extra == "postgres"
Requires-Dist: pg8000>=1.30.0; extra == "postgres"
Provides-Extra: oracle
Requires-Dist: oracledb>=3.4.0; extra == "oracle"
Requires-Dist: cx-Oracle>=8.3.0; extra == "oracle"
Provides-Extra: sqlserver
Requires-Dist: pyodbc>=5.3.0; extra == "sqlserver"
Requires-Dist: pymssql>=2.3.9; extra == "sqlserver"
Provides-Extra: redshift
Requires-Dist: redshift-connector>=2.1.5; extra == "redshift"
Requires-Dist: psycopg2-binary>=2.9.11; extra == "redshift"
Provides-Extra: bigquery
Requires-Dist: google-cloud-bigquery>=3.38.0; extra == "bigquery"
Requires-Dist: pandas-gbq>=0.19.0; extra == "bigquery"
Provides-Extra: performance
Requires-Dist: connectorx>=0.3.0; extra == "performance"
Requires-Dist: polars>=1.35.1; extra == "performance"
Requires-Dist: pyarrow>=20.0.0; extra == "performance"
Requires-Dist: dask>=2025.11.0; extra == "performance"
Provides-Extra: sqlalchemy
Requires-Dist: sqlalchemy>=2.0.0; extra == "sqlalchemy"
Provides-Extra: credentials
Requires-Dist: boto3>=1.26.0; extra == "credentials"
Requires-Dist: google-cloud-secret-manager>=2.16.0; extra == "credentials"
Requires-Dist: azure-identity>=1.12.0; extra == "credentials"
Requires-Dist: azure-keyvault-secrets>=4.6.0; extra == "credentials"
Requires-Dist: hvac>=1.1.0; extra == "credentials"
Requires-Dist: keyring>=24.0.0; extra == "credentials"
Provides-Extra: aws-credentials
Requires-Dist: boto3>=1.26.0; extra == "aws-credentials"
Provides-Extra: gcp-credentials
Requires-Dist: google-cloud-secret-manager>=2.16.0; extra == "gcp-credentials"
Provides-Extra: azure-credentials
Requires-Dist: azure-identity>=1.12.0; extra == "azure-credentials"
Requires-Dist: azure-keyvault-secrets>=4.6.0; extra == "azure-credentials"
Provides-Extra: vault-credentials
Requires-Dist: hvac>=1.1.0; extra == "vault-credentials"
Provides-Extra: keyring-credentials
Requires-Dist: keyring>=24.0.0; extra == "keyring-credentials"
Provides-Extra: all-drivers
Requires-Dist: PyMySQL>=1.1.2; extra == "all-drivers"
Requires-Dist: mysql-connector-python>=9.3.0; extra == "all-drivers"
Requires-Dist: mysqlclient>=2.2.0; extra == "all-drivers"
Requires-Dist: psycopg2-binary>=2.9.11; extra == "all-drivers"
Requires-Dist: psycopg>=3.1.0; extra == "all-drivers"
Requires-Dist: pg8000>=1.30.0; extra == "all-drivers"
Requires-Dist: oracledb>=3.4.0; extra == "all-drivers"
Requires-Dist: cx-Oracle>=8.3.0; extra == "all-drivers"
Requires-Dist: pyodbc>=5.3.0; extra == "all-drivers"
Requires-Dist: pymssql>=2.3.9; extra == "all-drivers"
Requires-Dist: redshift-connector>=2.1.5; extra == "all-drivers"
Requires-Dist: google-cloud-bigquery>=3.38.0; extra == "all-drivers"
Requires-Dist: pandas-gbq>=0.19.0; extra == "all-drivers"
Provides-Extra: full
Requires-Dist: PyMySQL>=1.1.2; extra == "full"
Requires-Dist: mysql-connector-python>=9.3.0; extra == "full"
Requires-Dist: mysqlclient>=2.2.0; extra == "full"
Requires-Dist: psycopg2-binary>=2.9.11; extra == "full"
Requires-Dist: psycopg>=3.1.0; extra == "full"
Requires-Dist: pg8000>=1.30.0; extra == "full"
Requires-Dist: oracledb>=3.4.0; extra == "full"
Requires-Dist: cx-Oracle>=8.3.0; extra == "full"
Requires-Dist: pyodbc>=5.3.0; extra == "full"
Requires-Dist: pymssql>=2.3.9; extra == "full"
Requires-Dist: redshift-connector>=2.1.5; extra == "full"
Requires-Dist: google-cloud-bigquery>=3.38.0; extra == "full"
Requires-Dist: pandas-gbq>=0.19.0; extra == "full"
Requires-Dist: connectorx>=0.3.0; extra == "full"
Requires-Dist: sqlalchemy>=2.0.0; extra == "full"
Requires-Dist: polars>=1.35.1; extra == "full"
Requires-Dist: dask>=2025.11.0; extra == "full"
Requires-Dist: pyarrow>=20.0.0; extra == "full"
Requires-Dist: boto3>=1.26.0; extra == "full"
Requires-Dist: google-cloud-secret-manager>=2.16.0; extra == "full"
Requires-Dist: azure-identity>=1.12.0; extra == "full"
Requires-Dist: azure-keyvault-secrets>=4.6.0; extra == "full"
Requires-Dist: hvac>=1.1.0; extra == "full"
Requires-Dist: keyring>=24.0.0; extra == "full"
Provides-Extra: dev
Requires-Dist: pytest>=9.0.0; extra == "dev"
Requires-Dist: pytest-cov>=7.0.0; extra == "dev"
Requires-Dist: pytest-xdist>=3.8.0; extra == "dev"
Requires-Dist: python-dotenv>=1.2.1; extra == "dev"
Requires-Dist: mock>=5.2.0; extra == "dev"
Requires-Dist: black>=25.11.0; extra == "dev"
Requires-Dist: flake8>=7.3.0; extra == "dev"
Requires-Dist: mypy>=1.18.2; extra == "dev"
Requires-Dist: isort>=7.0.0; extra == "dev"
Requires-Dist: coverage>=7.11.3; extra == "dev"
Dynamic: license-file
